{
    "kind": "SeldonDeployment",
    "apiVersion": "machinelearning.seldon.io/v1",
    "metadata": {
        "name": "seldon-deployment-example",
        "namespace": "staging",
        "creationTimestamp": null
    },
    "spec": {
        "predictors": [
            {
                "name": "seldon-deployment-example",
                "graph": null,
                "componentSpecs": [
                    {
                        "metadata": {
                            "name": "seldon-deployment-example",
                            "creationTimestamp": null
                        },
                        "spec": {
                            "containers": [
                                {
                                    "name": "",
                                    "image": "seldonio/sklearnserver_rest:0.2",
                                    "resources": {}
                                }
                            ]
                        }
                    }
                ],
                "replicas": 1,
                "engineResources": {},
                "svcOrchSpec": {},
                "explainer": {
                    "containerSpec": {
                        "name": "",
                        "resources": {}
                    }
                }
            }
        ]
    },
    "status": {}
}